qcanvas_backend/__init__.py
qcanvas_backend/database/__init__.py
qcanvas_backend/database/data_monolith.py
qcanvas_backend/database/qcanvas_database.py
qcanvas_backend/database/types/__init__.py
qcanvas_backend/database/types/canvas_database_types.py
qcanvas_backend/database/types/course_page_grouping_policy.py
qcanvas_backend/database/types/module_page_type.py
qcanvas_backend/database/types/resource_download_state.py
qcanvas_backend/database/types/resource_life_state.py
qcanvas_backend/gql_queries/__init__.py
qcanvas_backend/gql_queries/all_courses.gql
qcanvas_backend/gql_queries/all_courses.py
qcanvas_backend/gql_queries/canvas_course_data.gql
qcanvas_backend/gql_queries/canvas_course_data.py
qcanvas_backend/gql_queries/canvas_introspection.json
qcanvas_backend/gql_queries/course_mail.gql
qcanvas_backend/gql_queries/course_mail.py
qcanvas_backend/gql_queries/single_course.gql
qcanvas_backend/gql_queries/single_course.py
qcanvas_backend/net/__init__.py
qcanvas_backend/net/canvas/__init__.py
qcanvas_backend/net/canvas/canvas_data_aggregator.py
qcanvas_backend/net/canvas/canvas_page_loader.py
qcanvas_backend/net/canvas/course_mail_item.py
qcanvas_backend/net/canvas/page_with_content.py
qcanvas_backend/net/constants.py
qcanvas_backend/net/panopto/__init__.py
qcanvas_backend/net/panopto/folder_with_sessions.py
qcanvas_backend/net/panopto/iframe_panopto_video_extractor.py
qcanvas_backend/net/panopto/iframe_panopto_video_info.py
qcanvas_backend/net/panopto/panopto_data_aggregator.py
qcanvas_backend/net/panopto/video_downloader.py
qcanvas_backend/net/resources/__init__.py
qcanvas_backend/net/resources/download/__init__.py
qcanvas_backend/net/resources/download/download_progress.py
qcanvas_backend/net/resources/download/resource_manager.py
qcanvas_backend/net/resources/extracting/__init__.py
qcanvas_backend/net/resources/extracting/canvas_file_extractor.py
qcanvas_backend/net/resources/extracting/canvas_media_object_extractor.py
qcanvas_backend-0.3.0.dist-info/METADATA
qcanvas_backend-0.3.0.dist-info/WHEEL
qcanvas_backend-0.3.0.dist-info/RECORD
