Metadata-Version: 2.1
Name: qcanvas-backend
Version: 0.3.0
Summary: 
Author: QCanvas
Author-email: QCanvas@noreply.codeberg.org
Requires-Python: >=3.10,<4.0
Classifier: Programming Language :: Python :: 3
Classifier: Programming Language :: Python :: 3.10
Classifier: Programming Language :: Python :: 3.11
Classifier: Programming Language :: Python :: 3.12
Requires-Dist: SQLAlchemy (>=2.0.29,<3.0.0)
Requires-Dist: asynchronize (>=0.0.1,<0.0.2)
Requires-Dist: asynctaskpool (>=0.2.0,<0.3.0)
Requires-Dist: beautifulsoup4 (>=4.12.3,<5.0.0)
Requires-Dist: gql (>=3.5.0,<4.0.0)
Requires-Dist: httpx (>=0.27.0,<0.28.0)
Requires-Dist: lightdb (>=2.0,<3.0)
Requires-Dist: pydantic (>=2.7.0,<3.0.0)
Requires-Dist: python-dateutil (>=2.9.0.post0,<3.0.0)
Requires-Dist: qcanvas-api-clients (>=0.4.0,<0.5.0)
Requires-Dist: yt-dlp (>=2024.4.9)
